{
  "id" : "AOC24__Filter_16",
  "metainfo" : {
    "label" : "AOC24__Filter_16",
    "autoLayout" : true,
    "staleState" : "none",
    "sourceSuggestions" : {
      "sources" : [ ]
    },
    "graphConfig" : {
      "entityConfig" : {
        "materialized" : "ephemeral",
        "database" : "\"QA_DATABASE\"",
        "schema" : "\"PUBLIC\"",
        "type" : "ModelConfig"
      }
    },
    "version" : 3
  },
  "processes" : {
    "Filter_16_ZyxRdXZSW_mf-P2tW1EWh" : {
      "id" : "Filter_16_ZyxRdXZSW_mf-P2tW1EWh",
      "component" : "TargetModel",
      "metadata" : {
        "label" : "Filter_16"
      },
      "properties" : {
        "customQueryDisabled" : true,
        "customQuery" : false,
        "incrementalEditorDisabled" : true,
        "query" : "\nSELECT *\n\nFROM Filter_16\n\n",
        "isModel" : true,
        "incrementalKey" : false,
        "incremental" : {
          "expression" : "true"
        }
      },
      "ports" : {
        "inputs" : [ {
          "id" : "input_port_2",
          "slug" : "input_port_2"
        } ],
        "outputs" : [ {
          "id" : "output_port_2",
          "slug" : "output_port_2"
        } ],
        "isCustomOutputSchema" : false,
        "autoUpdateOnRun" : false
      }
    },
    "16" : {
      "id" : "16",
      "component" : "Filter",
      "metadata" : {
        "label" : "Filter_16",
        "x" : 4140,
        "y" : 180,
        "phase" : 0
      },
      "properties" : {
        "columnsSelector" : [ ],
        "condition" : {
          "expression" : "((((\"X-INT\" >= 2.0E14D) AND (\"X-INT\" <= 4.0E14D)) AND (\"Y-INT\" >= 2.0E14D)) AND (\"Y-INT\" <= 4.0E14D))",
          "_row_id" : null
        }
      },
      "ports" : {
        "inputs" : [ {
          "id" : "16_Input",
          "slug" : "in0"
        } ],
        "outputs" : [ {
          "id" : "ZyxRdXZSW_mf-P2tW1EWh",
          "slug" : "out0"
        } ],
        "isCustomOutputSchema" : false,
        "autoUpdateOnRun" : false
      }
    },
    "Filter_17_17_True" : {
      "id" : "Filter_17_17_True",
      "component" : "SQLStatement",
      "metadata" : {
        "label" : "Filter_17"
      },
      "properties" : {
        "fileTabs" : [ {
          "path" : "output_port_0",
          "id" : "output_port_0",
          "language" : "sql",
          "content" : "\nSELECT *\n\nFROM {{ ref('AOC24__Filter_17') }}\n\n"
        } ]
      },
      "ports" : {
        "inputs" : [ {
          "id" : "input_port_0",
          "slug" : "input_port_0"
        } ],
        "outputs" : [ {
          "id" : "output_port_0",
          "slug" : "output_port_0"
        } ],
        "isCustomOutputSchema" : false,
        "autoUpdateOnRun" : false
      }
    }
  },
  "connections" : [ {
    "id" : "conn_16_ZyxRdXZSW_mf-P2tW1EWh_Filter_16_ZyxRdXZSW_mf-P2tW1EWh",
    "source" : "16",
    "sourcePort" : "ZyxRdXZSW_mf-P2tW1EWh",
    "target" : "Filter_16_ZyxRdXZSW_mf-P2tW1EWh",
    "targetPort" : "input_port_2",
    "isWireless" : false
  }, {
    "id" : "edge_99",
    "source" : "Filter_17_17_True",
    "sourcePort" : "output_port_0",
    "target" : "16",
    "targetPort" : "16_Input",
    "isWireless" : false
  } ],
  "component" : "Model"
}