{
  "id" : "m_mmrt_loan_cal_hist_sum_load__SM_LOAN_CAL_MTH_END_HIST",
  "metainfo" : {
    "label" : "m_mmrt_loan_cal_hist_sum_load__SM_LOAN_CAL_MTH_END_HIST",
    "autoLayout" : true,
    "staleState" : "none",
    "sourceSuggestions" : {
      "sources" : [ ]
    },
    "graphConfig" : {
      "entityConfig" : {
        "alias" : "\"SM_LOAN_CAL_MTH_END_HIST\"",
        "materialized" : "table",
        "database" : "\"tanmay\"",
        "schema" : "\"default\"",
        "type" : "ModelConfig"
      }
    },
    "version" : 3
  },
  "processes" : {
    "SM_LOAN_CAL_MTH_END_HIST" : {
      "id" : "SM_LOAN_CAL_MTH_END_HIST",
      "component" : "TargetModel",
      "metadata" : {
        "label" : "SM_LOAN_CAL_MTH_END_HIST",
        "phase" : 1
      },
      "properties" : {
        "customQueryDisabled" : true,
        "customQuery" : false,
        "incrementalEditorDisabled" : true,
        "query" : "\nSELECT *\n\nFROM EXP_CURRENT_DELINQUENCY_EXPR_8\n\n",
        "isModel" : true,
        "incrementalKey" : false,
        "incremental" : {
          "expression" : "true"
        }
      },
      "ports" : {
        "inputs" : [ {
          "id" : "SM_LOAN_CAL_MTH_END_HIST_in0",
          "slug" : "in0"
        } ],
        "outputs" : [ {
          "id" : "69_DXo0wZeK5VNk8tsIi7",
          "slug" : "out0"
        } ],
        "isCustomOutputSchema" : false,
        "autoUpdateOnRun" : false
      }
    },
    "EXP_CURRENT_DELINQUENCY_EXPR_8" : {
      "id" : "EXP_CURRENT_DELINQUENCY_EXPR_8",
      "component" : "Reformat",
      "metadata" : {
        "label" : "EXP_CURRENT_DELINQUENCY_EXPR_8",
        "x" : 420,
        "y" : 20,
        "phase" : 1
      },
      "properties" : {
        "columnsSelector" : [ "EXP_CURRENT_DELINQUENCY_EXPR_8_in0##ACC_NUM", "EXP_CURRENT_DELINQUENCY_EXPR_8_in0##PAST_DUE", "EXP_CURRENT_DELINQUENCY_EXPR_8_in0##BLOCK_CODE", "EXP_CURRENT_DELINQUENCY_EXPR_8_in0##CHARGE_OFF_AMOUNT", "EXP_CURRENT_DELINQUENCY_EXPR_8_in0##CURR_BALANCE", "EXP_CURRENT_DELINQUENCY_EXPR_8_in0##CYCLE_DAY", "EXP_CURRENT_DELINQUENCY_EXPR_8_in0##GOOD_BAD_FLAG", "EXP_CURRENT_DELINQUENCY_EXPR_8_in0##PAYMENT_METHOD", "EXP_CURRENT_DELINQUENCY_EXPR_8_in0##SCORE", "EXP_CURRENT_DELINQUENCY_EXPR_8_in0##CURRENT_DEINQUENCY", "EXP_CURRENT_DELINQUENCY_EXPR_8_in0##UNEARNED_INTEREST", "EXP_CURRENT_DELINQUENCY_EXPR_8_in0##REBATE_PROMOTION_INDICATOR", "EXP_CURRENT_DELINQUENCY_EXPR_8_in0##PERIODID", "EXP_CURRENT_DELINQUENCY_EXPR_8_in0##STATUS", "EXP_CURRENT_DELINQUENCY_EXPR_8_in0##ARREARS_VALUE", "EXP_CURRENT_DELINQUENCY_EXPR_8_in0##USER_CODE_1", "EXP_CURRENT_DELINQUENCY_EXPR_8_in0##USER_CODE_2" ],
        "expressions" : [ {
          "expression" : {
            "expression" : "ACC_NUM"
          },
          "alias" : "LN_ACCOUNT_NUMBER",
          "_row_id" : "MQCE_0Pjq8l8F2bIvYXyR"
        }, {
          "expression" : {
            "expression" : "PAST_DUE"
          },
          "alias" : "LN_PAST_DUE",
          "_row_id" : "QDEEZpLlFtoMmwjCCrq3A"
        }, {
          "expression" : {
            "expression" : "BLOCK_CODE"
          },
          "alias" : "LN_BLOCK_CODE",
          "_row_id" : "cYbulVg70cB4YnHSe4maf"
        }, {
          "expression" : {
            "expression" : "CHARGE_OFF_AMOUNT"
          },
          "alias" : "LN_CHARGE_OFF_AMOUNT",
          "_row_id" : "GihTy7O38F-EvMf9YY-Wj"
        }, {
          "expression" : {
            "expression" : "CURR_BALANCE"
          },
          "alias" : "LN_CURRENT_BALANCE",
          "_row_id" : "T_gg0qcdz8RzLiQq-TWRE"
        }, {
          "expression" : {
            "expression" : "CYCLE_DAY"
          },
          "alias" : "LN_CYCLE_DAY",
          "_row_id" : "0fZvW9nptdAxhlI-HFCHU"
        }, {
          "expression" : {
            "expression" : "GOOD_BAD_FLAG"
          },
          "alias" : "LN_GOOD_BAD_FLAG",
          "_row_id" : "nvnA2FsNPaDc7E8Fdh9wP"
        }, {
          "expression" : {
            "expression" : "PAYMENT_METHOD"
          },
          "alias" : "LN_PAYMENT_METHOD",
          "_row_id" : "tAyu8XMFxovoHxW0VBxL0"
        }, {
          "expression" : {
            "expression" : "SCORE"
          },
          "alias" : "LN_BEHAVIOUR_SCORE",
          "_row_id" : "AKaU043O8eD-I0HAxz00T"
        }, {
          "expression" : {
            "expression" : "CURRENT_DEINQUENCY"
          },
          "alias" : "LN_CURRENT_DELINQUENCY",
          "_row_id" : "h0bmK4XnAQT0qmnccMS-h"
        }, {
          "expression" : {
            "expression" : "UNEARNED_INTEREST"
          },
          "alias" : "LN_UNEARNED_INTEREST",
          "_row_id" : "XEyG_gAThAnGVnstgUTuy"
        }, {
          "expression" : {
            "expression" : "REBATE_PROMOTION_INDICATOR"
          },
          "alias" : "LN_REBATE_PROMOTION_INDICATOR",
          "_row_id" : "sRxgw6mRjSLtMwurbc-wd"
        }, {
          "expression" : {
            "expression" : "PERIODID"
          },
          "alias" : "PERIODID",
          "_row_id" : "m1PvlExgLq5aVOahrCJHD"
        }, {
          "expression" : {
            "expression" : "STATUS"
          },
          "alias" : "LN_ACCOUNT_STATUS",
          "_row_id" : "st7ByZyd67SlLwsLPk9qS"
        }, {
          "expression" : {
            "expression" : "ARREARS_VALUE"
          },
          "alias" : "LN_ARREARS_VALUE",
          "_row_id" : "MYGCjIj3b3yvKsyHVP7Zt"
        }, {
          "expression" : {
            "expression" : "USER_CODE_1"
          },
          "alias" : "LN_USER_CODE_1",
          "_row_id" : "2JWVycpb-x4rV8SWbW3XQ"
        }, {
          "expression" : {
            "expression" : "USER_CODE_2"
          },
          "alias" : "LN_USER_CODE_2",
          "_row_id" : "uyEEPe_xu-CtnCCKAAvaY"
        } ]
      },
      "ports" : {
        "inputs" : [ {
          "id" : "EXP_CURRENT_DELINQUENCY_EXPR_8_in0",
          "slug" : "in0"
        } ],
        "outputs" : [ {
          "id" : "EXP_CURRENT_DELINQUENCY_EXPR_8_out0",
          "slug" : "out0"
        } ],
        "isCustomOutputSchema" : false,
        "autoUpdateOnRun" : false
      }
    },
    "EXP_CURRENT_DELINQUENCY_EXP_CURRENT_DELINQUENCY_out0" : {
      "id" : "EXP_CURRENT_DELINQUENCY_EXP_CURRENT_DELINQUENCY_out0",
      "component" : "SQLStatement",
      "metadata" : {
        "label" : "EXP_CURRENT_DELINQUENCY"
      },
      "properties" : {
        "fileTabs" : [ {
          "path" : "output_port_1",
          "id" : "output_port_1",
          "language" : "sql",
          "content" : "\nSELECT *\n\nFROM {{ ref('m_mmrt_loan_cal_hist_sum_load__EXP_CURRENT_DELINQUENCY') }}\n\n"
        } ]
      },
      "ports" : {
        "inputs" : [ {
          "id" : "input_port_1",
          "slug" : "input_port_1"
        } ],
        "outputs" : [ {
          "id" : "output_port_1",
          "slug" : "output_port_1"
        } ],
        "isCustomOutputSchema" : false,
        "autoUpdateOnRun" : false
      }
    }
  },
  "connections" : [ {
    "id" : "edge_110",
    "source" : "EXP_CURRENT_DELINQUENCY_EXPR_8",
    "sourcePort" : "EXP_CURRENT_DELINQUENCY_EXPR_8_out0",
    "target" : "SM_LOAN_CAL_MTH_END_HIST",
    "targetPort" : "SM_LOAN_CAL_MTH_END_HIST_in0",
    "isWireless" : false
  }, {
    "id" : "edge_112",
    "source" : "EXP_CURRENT_DELINQUENCY_EXP_CURRENT_DELINQUENCY_out0",
    "sourcePort" : "output_port_1",
    "target" : "EXP_CURRENT_DELINQUENCY_EXPR_8",
    "targetPort" : "EXP_CURRENT_DELINQUENCY_EXPR_8_in0",
    "isWireless" : false
  } ],
  "component" : "Model"
}