{
  "id" : "sdff",
  "metainfo" : {
    "label" : "sdff",
    "autoLayout" : false,
    "version" : 1,
    "configuration" : {
      "schema" : {
        "type" : "record",
        "fields" : [ ]
      }
    },
    "isTranspiledPipeline" : false,
    "publishDiagnosticMetrics" : false,
    "processesVsModelFiles" : {
      "Unpivot_0_SWT8HCbcHTkoDUgCSubCk$$pzjOB0sFADV67KkiIY2FM" : "models/sdff/sdff__Unpivot_0.sql",
      "iLWqToK4kc14bemEAkrD5$$og7C5_tY-WHtK9Qx2-Gww" : "models/sdff/sdff__Unpivot_0.sql"
    }
  },
  "processes" : {
    "iLWqToK4kc14bemEAkrD5$$og7C5_tY-WHtK9Qx2-Gww" : {
      "id" : "iLWqToK4kc14bemEAkrD5$$og7C5_tY-WHtK9Qx2-Gww",
      "component" : "Model",
      "metadata" : {
        "label" : "sdff__Unpivot_0",
        "phase" : 0
      },
      "properties" : {
        "modelName" : "sdff__Unpivot_0"
      },
      "visualMetaInfo" : {
        "visualProcessIds" : [ "Unpivot_0_SWT8HCbcHTkoDUgCSubCk$$pzjOB0sFADV67KkiIY2FM", "iLWqToK4kc14bemEAkrD5$$og7C5_tY-WHtK9Qx2-Gww" ],
        "type" : "ephemeral",
        "isTemporaryTable" : true,
        "lastNodeProcessIds" : [ "Unpivot_0_SWT8HCbcHTkoDUgCSubCk$$pzjOB0sFADV67KkiIY2FM" ]
      },
      "ports" : {
        "inputs" : [ ],
        "outputs" : [ {
          "id" : "sdff__Unpivot_0_out_0",
          "slug" : "out_0"
        } ],
        "isCustomOutputSchema" : false
      }
    }
  },
  "connections" : [ ],
  "component" : "Pipeline"
}