{
  "id" : "m_rep_cards_orig_client_preference_update__UPD_CLIENT_PREFERENCE",
  "metainfo" : {
    "label" : "m_rep_cards_orig_client_preference_update__UPD_CLIENT_PREFERENCE",
    "autoLayout" : true,
    "staleState" : "none",
    "sourceSuggestions" : {
      "sources" : [ ]
    },
    "graphConfig" : {
      "entityConfig" : {
        "alias" : "\"UPD_CLIENT_PREFERENCE\"",
        "materialized" : "table",
        "database" : "\"prophecy-databricks-qa\"",
        "schema" : "\"pramit_test\"",
        "type" : "ModelConfig"
      }
    },
    "version" : 3
  },
  "processes" : {
    "RTR_CARDS_ORIG_CLIENT_PREFERENCE_EXPR_UPDATE_CLIENT_PREFERENCE" : {
      "id" : "RTR_CARDS_ORIG_CLIENT_PREFERENCE_EXPR_UPDATE_CLIENT_PREFERENCE",
      "component" : "Reformat",
      "metadata" : {
        "label" : "RTR_CARDS_ORIG_CLIENT_PREFERENCE_EXPR_UPDATE_CLIENT_PREFERENCE",
        "x" : 820,
        "y" : 20,
        "phase" : 1
      },
      "properties" : {
        "columnsSelector" : [ ],
        "expressions" : [ {
          "expression" : {
            "expression" : "CLID_CLIENT_ALIAS",
            "_row_id" : null
          },
          "alias" : "CLID_CLIENT_ALIAS3",
          "description" : null,
          "_row_id" : "jABL9dGWI1P0O2gqVZWoE"
        }, {
          "expression" : {
            "expression" : "CLID_CLIENT_PREFERENCE",
            "_row_id" : null
          },
          "alias" : "CLID_CLIENT_PREFERENCE3",
          "description" : null,
          "_row_id" : "dAqhrUycqGBVQDxJZXgEv"
        }, {
          "expression" : {
            "expression" : "MARKETING_OPT_IN_TEL",
            "_row_id" : null
          },
          "alias" : "MARKETING_OPT_IN_TEL3",
          "description" : null,
          "_row_id" : "53KHRc0-uuSo7xVtQ48Ht"
        }, {
          "expression" : {
            "expression" : "MARKETING_OPT_IN_EMAIL",
            "_row_id" : null
          },
          "alias" : "MARKETING_OPT_IN_EMAIL3",
          "description" : null,
          "_row_id" : "IhFB3v38KpYP-WVe5zhFl"
        }, {
          "expression" : {
            "expression" : "MARKETING_OPT_IN_TEXT",
            "_row_id" : null
          },
          "alias" : "MARKETING_OPT_IN_TEXT3",
          "description" : null,
          "_row_id" : "ja1qME3yZjILEhs-_sf4K"
        }, {
          "expression" : {
            "expression" : "MARKETING_OPT_IN_POST",
            "_row_id" : null
          },
          "alias" : "MARKETING_OPT_IN_POST3",
          "description" : null,
          "_row_id" : "v1lVMjkC0Yv4Kqr2v3PiZ"
        }, {
          "expression" : {
            "expression" : "MAIL_PREFERENCE",
            "_row_id" : null
          },
          "alias" : "MAIL_PREFERENCE3",
          "description" : null,
          "_row_id" : "twIeYWL6--7CRUYKBCxZJ"
        }, {
          "expression" : {
            "expression" : "MAIL_PREFERENCE_DATE",
            "_row_id" : null
          },
          "alias" : "MAIL_PREFERENCE_DATE3",
          "description" : null,
          "_row_id" : "-238Ll8FAHjUK_JvLs_9J"
        }, {
          "expression" : {
            "expression" : "PHONE_PREFERENCE",
            "_row_id" : null
          },
          "alias" : "PHONE_PREFERENCE3",
          "description" : null,
          "_row_id" : "vv3XOUWUnx_66errhDkfT"
        }, {
          "expression" : {
            "expression" : "PHONE_PREFERENCE_DATE",
            "_row_id" : null
          },
          "alias" : "PHONE_PREFERENCE_DATE3",
          "description" : null,
          "_row_id" : "YL9wzWaZ5h21RTMBaDV95"
        }, {
          "expression" : {
            "expression" : "EMAIL_PREFERENCE",
            "_row_id" : null
          },
          "alias" : "EMAIL_PREFERENCE3",
          "description" : null,
          "_row_id" : "qWhfRVqE4tF8oMNUIgtLt"
        }, {
          "expression" : {
            "expression" : "EMAIL_PREFERENCE_DATE",
            "_row_id" : null
          },
          "alias" : "EMAIL_PREFERENCE_DATE3",
          "description" : null,
          "_row_id" : "j3SvgQRy-g8f-aoUAn822"
        }, {
          "expression" : {
            "expression" : "SOURCE_SYSTEM_CODE",
            "_row_id" : null
          },
          "alias" : "SOURCE_SYSTEM_CODE3",
          "description" : null,
          "_row_id" : "b7mBLNkHwByn5qvXznmHt"
        }, {
          "expression" : {
            "expression" : "business_date",
            "_row_id" : null
          },
          "alias" : "business_date3",
          "description" : null,
          "_row_id" : "KkU8QxyBgUxt6POOHfSyT"
        }, {
          "expression" : {
            "expression" : "ROW_NUMBER",
            "_row_id" : null
          },
          "alias" : "ROW_NUMBER3",
          "description" : null,
          "_row_id" : "AxyF6tvP9ROk-M-CVBO2M"
        }, {
          "expression" : {
            "expression" : "TOTAL_COMPARE",
            "_row_id" : null
          },
          "alias" : "TOTAL_COMPARE3",
          "description" : null,
          "_row_id" : "usVGKwOZ02pPzYvktsoLo"
        } ]
      },
      "ports" : {
        "inputs" : [ {
          "id" : "RTR_CARDS_ORIG_CLIENT_PREFERENCE_EXPR_UPDATE_CLIENT_PREFERENCE_in0",
          "slug" : "in0"
        } ],
        "outputs" : [ {
          "id" : "RTR_CARDS_ORIG_CLIENT_PREFERENCE_EXPR_UPDATE_CLIENT_PREFERENCE_out0",
          "slug" : "out0"
        } ],
        "isCustomOutputSchema" : false,
        "autoUpdateOnRun" : false
      }
    },
    "7AXML9HJCgzK3PakSev1U" : {
      "id" : "7AXML9HJCgzK3PakSev1U",
      "component" : "Reformat",
      "metadata" : {
        "label" : "UPD_CLIENT_PREFERENCE1_add_missing_column_0",
        "x" : 1020,
        "y" : 20,
        "phase" : 0
      },
      "properties" : {
        "columnsSelector" : [ ],
        "expressions" : [ {
          "expression" : {
            "expression" : "CAST(NULL AS STRING)",
            "_row_id" : null
          },
          "alias" : "MPS_PREFERENCE",
          "description" : null,
          "_row_id" : "XYFtUxj35N3W8oIMtkP-0"
        }, {
          "expression" : {
            "expression" : "CAST(NULL AS TIMESTAMP)",
            "_row_id" : null
          },
          "alias" : "MPS_PREFERENCE_DATE",
          "description" : null,
          "_row_id" : "ZoFCO-8p0IYgGFOlInAKc"
        }, {
          "expression" : {
            "expression" : "CAST(NULL AS STRING)",
            "_row_id" : null
          },
          "alias" : "TPS_PREFERENCE",
          "description" : null,
          "_row_id" : "FXCOXmWFB0_NZP-85bUEj"
        }, {
          "expression" : {
            "expression" : "CAST(NULL AS TIMESTAMP)",
            "_row_id" : null
          },
          "alias" : "TPS_PREFERENCE_DATE",
          "description" : null,
          "_row_id" : "mWE-8yqaZApv1_vWWf364"
        }, {
          "expression" : {
            "expression" : "CAST(NULL AS STRING)",
            "_row_id" : null
          },
          "alias" : "ICOS_PREFERENCE",
          "description" : null,
          "_row_id" : "xP5CWmKhmihDJC2r2QyUr"
        }, {
          "expression" : {
            "expression" : "CAST(NULL AS TIMESTAMP)",
            "_row_id" : null
          },
          "alias" : "ICOS_PREFERENCE_DATE",
          "description" : null,
          "_row_id" : "3aTyeVXzRy5coSXJSlgEz"
        }, {
          "expression" : {
            "expression" : "*",
            "_row_id" : null
          },
          "alias" : null,
          "description" : null,
          "_row_id" : null
        } ]
      },
      "ports" : {
        "inputs" : [ {
          "id" : "0ZfJhYBPAGNg9Dld-Uucz",
          "slug" : "in0"
        } ],
        "outputs" : [ {
          "id" : "ZCzmSTchGVH8ChLMk9r_4",
          "slug" : "out"
        } ],
        "isCustomOutputSchema" : false,
        "autoUpdateOnRun" : false
      }
    },
    "EXP_CARDS_ORIG_CLIENT_PREFERENCE_EXP_CARDS_ORIG_CLIENT_PREFERENCE_out0" : {
      "id" : "EXP_CARDS_ORIG_CLIENT_PREFERENCE_EXP_CARDS_ORIG_CLIENT_PREFERENCE_out0",
      "component" : "SQLStatement",
      "metadata" : {
        "label" : "EXP_CARDS_ORIG_CLIENT_PREFERENCE"
      },
      "properties" : {
        "fileTabs" : [ {
          "path" : "output_port_1",
          "id" : "output_port_1",
          "language" : "sql",
          "content" : "\nSELECT *\n\nFROM {{ ref('m_rep_cards_orig_client_preference_update__EXP_CARDS_ORIG_CLIENT_PREFERENCE') }}\n\n"
        } ]
      },
      "ports" : {
        "inputs" : [ {
          "id" : "input_port_1",
          "slug" : "input_port_1"
        } ],
        "outputs" : [ {
          "id" : "output_port_1",
          "slug" : "output_port_1"
        } ],
        "isCustomOutputSchema" : false,
        "autoUpdateOnRun" : false
      }
    },
    "mu8GD_1T4QpExSfeBzwfL" : {
      "id" : "mu8GD_1T4QpExSfeBzwfL",
      "component" : "Filter",
      "metadata" : {
        "label" : "RTR_CARDS_ORIG_CLIENT_PREFERENCE_out1",
        "x" : 620,
        "y" : 20,
        "phase" : 0
      },
      "properties" : {
        "columnsSelector" : [ ],
        "condition" : {
          "expression" : "(((CLID_CLIENT_PREFERENCE IS NOT NULL) AND (TOTAL_COMPARE > 0)) AND (ROW_NUMBER = 1))",
          "_row_id" : null
        }
      },
      "ports" : {
        "inputs" : [ {
          "id" : "gWvcKGRjodKsjqHkaWLu4",
          "slug" : "in0"
        } ],
        "outputs" : [ {
          "id" : "QJ1DWI79EmRBjawbP5nSw",
          "slug" : "out0"
        } ],
        "isCustomOutputSchema" : false,
        "autoUpdateOnRun" : false
      }
    },
    "UPD_CLIENT_PREFERENCE_EXP" : {
      "id" : "UPD_CLIENT_PREFERENCE_EXP",
      "component" : "Reformat",
      "metadata" : {
        "label" : "UPD_CLIENT_PREFERENCE_EXP",
        "x" : 1220,
        "y" : 20,
        "phase" : 1
      },
      "properties" : {
        "columnsSelector" : [ ],
        "expressions" : [ {
          "expression" : {
            "expression" : "CLID_CLIENT_PREFERENCE3",
            "_row_id" : null
          },
          "alias" : "CLID",
          "description" : null,
          "_row_id" : "yQPdPqB7ppmU91rBFN_I4"
        }, {
          "expression" : {
            "expression" : "SOURCE_SYSTEM_CODE3",
            "_row_id" : null
          },
          "alias" : "SOURCE_SYSTEM_CODE",
          "description" : null,
          "_row_id" : "RkIymNts_Bvvjrz6cEGmo"
        }, {
          "expression" : {
            "expression" : "MARKETING_OPT_IN_POST3",
            "_row_id" : null
          },
          "alias" : "MAIL_PREFERENCE",
          "description" : null,
          "_row_id" : "G_tUzFOFS2VDsKRiDzpGo"
        }, {
          "expression" : {
            "expression" : "business_date3",
            "_row_id" : null
          },
          "alias" : "MAIL_PREFERENCE_DATE",
          "description" : null,
          "_row_id" : "r0U2TPEDmo0rIIvHEXdO5"
        }, {
          "expression" : {
            "expression" : "MARKETING_OPT_IN_TEL3",
            "_row_id" : null
          },
          "alias" : "PHONE_PREFERENCE",
          "description" : null,
          "_row_id" : "to7sKf7QZJosZuwEIN7GJ"
        }, {
          "expression" : {
            "expression" : "business_date3",
            "_row_id" : null
          },
          "alias" : "PHONE_PREFERENCE_DATE",
          "description" : null,
          "_row_id" : "LGoFQtwa91UooW4D3oP5b"
        }, {
          "expression" : {
            "expression" : "MARKETING_OPT_IN_EMAIL3",
            "_row_id" : null
          },
          "alias" : "EMAIL_PREFERENCE",
          "description" : null,
          "_row_id" : "K5_6OJ1WXGo5JuetlNFIn"
        }, {
          "expression" : {
            "expression" : "business_date3",
            "_row_id" : null
          },
          "alias" : "EMAIL_PREFERENCE_DATE",
          "description" : null,
          "_row_id" : "kFmuIqD7os23JQGDKNXA_"
        }, {
          "expression" : {
            "expression" : "MARKETING_OPT_IN_TEXT3",
            "_row_id" : null
          },
          "alias" : "SMS_PREFERENCE",
          "description" : null,
          "_row_id" : "B1nz3OhoGv2mwGqQ7fC75"
        }, {
          "expression" : {
            "expression" : "business_date3",
            "_row_id" : null
          },
          "alias" : "SMS_PREFERENCE_DATE",
          "description" : null,
          "_row_id" : "0zEkCHHqTLjZq2sptUBf0"
        }, {
          "expression" : {
            "expression" : "CAST(NULL AS STRING)",
            "_row_id" : null
          },
          "alias" : "MPS_PREFERENCE",
          "description" : null,
          "_row_id" : "2UIdSjbqYa6cYPGU8B_C0"
        }, {
          "expression" : {
            "expression" : "CAST(NULL AS STRING)",
            "_row_id" : null
          },
          "alias" : "MPS_PREFERENCE_DATE",
          "description" : null,
          "_row_id" : "gthjkCR0S4X0kY5GDGSTc"
        }, {
          "expression" : {
            "expression" : "CAST(NULL AS STRING)",
            "_row_id" : null
          },
          "alias" : "TPS_PREFERENCE",
          "description" : null,
          "_row_id" : "Ls0WSQjFvWdTHxai-tVL-"
        }, {
          "expression" : {
            "expression" : "CAST(NULL AS STRING)",
            "_row_id" : null
          },
          "alias" : "TPS_PREFERENCE_DATE",
          "description" : null,
          "_row_id" : "W_5UCsEnhqsYbubB0kq4z"
        }, {
          "expression" : {
            "expression" : "CAST(NULL AS STRING)",
            "_row_id" : null
          },
          "alias" : "ICOS_PREFERENCE",
          "description" : null,
          "_row_id" : "Fl8Wk6TQB1JSKIQ5WpVA7"
        }, {
          "expression" : {
            "expression" : "CAST(NULL AS STRING)",
            "_row_id" : null
          },
          "alias" : "ICOS_PREFERENCE_DATE",
          "description" : null,
          "_row_id" : "zT2bElAyFWGD_lustqzzl"
        } ]
      },
      "ports" : {
        "inputs" : [ {
          "id" : "UPD_CLIENT_PREFERENCE_EXP_in0",
          "slug" : "in0"
        } ],
        "outputs" : [ {
          "id" : "UPD_CLIENT_PREFERENCE_EXP_out0",
          "slug" : "out0"
        } ],
        "isCustomOutputSchema" : false,
        "autoUpdateOnRun" : false
      }
    },
    "UPD_CLIENT_PREFERENCE" : {
      "id" : "UPD_CLIENT_PREFERENCE",
      "component" : "TargetModel",
      "metadata" : {
        "label" : "UPD_CLIENT_PREFERENCE",
        "phase" : 1
      },
      "properties" : {
        "customQueryDisabled" : true,
        "customQuery" : false,
        "incrementalEditorDisabled" : true,
        "query" : "\nSELECT *\n\nFROM UPD_CLIENT_PREFERENCE_EXP\n\n",
        "isModel" : true,
        "incrementalKey" : false,
        "incremental" : {
          "expression" : "true"
        }
      },
      "ports" : {
        "inputs" : [ {
          "id" : "UPD_CLIENT_PREFERENCE_in0",
          "slug" : "in0"
        } ],
        "outputs" : [ {
          "id" : "ZJG5B2s9omc9ZU11fLxZB",
          "slug" : "out0"
        } ],
        "isCustomOutputSchema" : false,
        "autoUpdateOnRun" : false
      }
    }
  },
  "connections" : [ {
    "id" : "edge_18",
    "source" : "UPD_CLIENT_PREFERENCE_EXP",
    "sourcePort" : "UPD_CLIENT_PREFERENCE_EXP_out0",
    "target" : "UPD_CLIENT_PREFERENCE",
    "targetPort" : "UPD_CLIENT_PREFERENCE_in0",
    "isWireless" : false
  }, {
    "id" : "edge_21",
    "source" : "7AXML9HJCgzK3PakSev1U",
    "sourcePort" : "ZCzmSTchGVH8ChLMk9r_4",
    "target" : "UPD_CLIENT_PREFERENCE_EXP",
    "targetPort" : "UPD_CLIENT_PREFERENCE_EXP_in0",
    "isWireless" : false
  }, {
    "id" : "edge_22",
    "source" : "RTR_CARDS_ORIG_CLIENT_PREFERENCE_EXPR_UPDATE_CLIENT_PREFERENCE",
    "sourcePort" : "RTR_CARDS_ORIG_CLIENT_PREFERENCE_EXPR_UPDATE_CLIENT_PREFERENCE_out0",
    "target" : "7AXML9HJCgzK3PakSev1U",
    "targetPort" : "0ZfJhYBPAGNg9Dld-Uucz",
    "isWireless" : false
  }, {
    "id" : "edge_27",
    "source" : "mu8GD_1T4QpExSfeBzwfL",
    "sourcePort" : "QJ1DWI79EmRBjawbP5nSw",
    "target" : "RTR_CARDS_ORIG_CLIENT_PREFERENCE_EXPR_UPDATE_CLIENT_PREFERENCE",
    "targetPort" : "RTR_CARDS_ORIG_CLIENT_PREFERENCE_EXPR_UPDATE_CLIENT_PREFERENCE_in0",
    "isWireless" : false
  }, {
    "id" : "edge_28",
    "source" : "EXP_CARDS_ORIG_CLIENT_PREFERENCE_EXP_CARDS_ORIG_CLIENT_PREFERENCE_out0",
    "sourcePort" : "output_port_1",
    "target" : "mu8GD_1T4QpExSfeBzwfL",
    "targetPort" : "gWvcKGRjodKsjqHkaWLu4",
    "isWireless" : false
  } ],
  "component" : "Model"
}