{
  "id" : "m_rep_cards_orig_client_staging_update__MINERVA_EXCEPTION_NEW_RECORD",
  "metainfo" : {
    "label" : "m_rep_cards_orig_client_staging_update__MINERVA_EXCEPTION_NEW_RECORD",
    "autoLayout" : true,
    "staleState" : "none",
    "sourceSuggestions" : {
      "sources" : [ ]
    },
    "graphConfig" : {
      "entityConfig" : {
        "alias" : "\"MINERVA_EXCEPTION_NEW_RECORD\"",
        "materialized" : "table",
        "database" : "\"prophecy-databricks-qa\"",
        "schema" : "\"pramit_test\"",
        "type" : "ModelConfig"
      }
    },
    "version" : 3
  },
  "processes" : {
    "MINERVA_EXCEPTION_NEW_RECORD" : {
      "id" : "MINERVA_EXCEPTION_NEW_RECORD",
      "component" : "TargetModel",
      "metadata" : {
        "label" : "MINERVA_EXCEPTION_NEW_RECORD",
        "phase" : 1
      },
      "properties" : {
        "customQueryDisabled" : true,
        "customQuery" : false,
        "incrementalEditorDisabled" : true,
        "query" : "\nSELECT *\n\nFROM MINERVA_EXCEPTION_NEW_RECORD_EXP\n\n",
        "isModel" : true,
        "incrementalKey" : false,
        "incremental" : {
          "expression" : "true"
        }
      },
      "ports" : {
        "inputs" : [ {
          "id" : "MINERVA_EXCEPTION_NEW_RECORD_in0",
          "slug" : "in0"
        } ],
        "outputs" : [ {
          "id" : "pID4eyFiwa9KY2g6aO85m",
          "slug" : "out0"
        } ],
        "isCustomOutputSchema" : false,
        "autoUpdateOnRun" : false
      }
    },
    "EXP_CONV_2" : {
      "id" : "EXP_CONV_2",
      "component" : "Reformat",
      "metadata" : {
        "label" : "EXP_CONV_2",
        "x" : 2320,
        "y" : 1020,
        "phase" : 1
      },
      "properties" : {
        "columnsSelector" : [ ],
        "expressions" : [ {
          "expression" : {
            "expression" : "5003",
            "_row_id" : null
          },
          "alias" : "CLASS",
          "description" : null,
          "_row_id" : "g-2llWO-YjCGrzyP3lU9c"
        }, {
          "expression" : {
            "expression" : "CLID",
            "_row_id" : null
          },
          "alias" : "CLID",
          "description" : null,
          "_row_id" : "XiaEfTICwzDI2xMZiKSs3"
        }, {
          "expression" : {
            "expression" : "business_date",
            "_row_id" : null
          },
          "alias" : "BUSINESS_DATE",
          "description" : null,
          "_row_id" : "EAQZcC7fQKHT5Sy7QMhlF"
        }, {
          "expression" : {
            "expression" : "'U'",
            "_row_id" : null
          },
          "alias" : "SOURCE_SYSTEM_CODE",
          "description" : null,
          "_row_id" : "cHmuqZ0PNH43lz3ymF0el"
        }, {
          "expression" : {
            "expression" : "SOURCE_CUSTOMER_REF",
            "_row_id" : null
          },
          "alias" : "SOURCE_CLIENT_REF",
          "description" : null,
          "_row_id" : "nRbzU_yLTBiwbukfSYaGI"
        }, {
          "expression" : {
            "expression" : "16",
            "_row_id" : null
          },
          "alias" : "ERROR_NUMBER",
          "description" : null,
          "_row_id" : "hkzgLECv6VgmEdHvSKMnx"
        }, {
          "expression" : {
            "expression" : "'m_rep_cards_orig_client_staging_update'",
            "_row_id" : null
          },
          "alias" : "PROCESS_NAME",
          "description" : null,
          "_row_id" : "nNjyWcrJVJkNfrvkubJdz"
        }, {
          "expression" : {
            "expression" : "'EXP_GENERIC_NAME_REFORMAT'",
            "_row_id" : null
          },
          "alias" : "FUNCTION_NAME",
          "description" : null,
          "_row_id" : "eDBssudGflj_0SizZJEYR"
        }, {
          "expression" : {
            "expression" : "'Y'",
            "_row_id" : null
          },
          "alias" : "LOAD_INDICATOR",
          "description" : null,
          "_row_id" : "C9lexlBoqdg3WtanO8Ki8"
        }, {
          "expression" : {
            "expression" : "(CONCAT('Salacious Surname', SURNAME))",
            "_row_id" : null
          },
          "alias" : "EXCEPTION_COMMENT",
          "description" : null,
          "_row_id" : "4ubM2mElPut1jM3Lmtq5j"
        } ]
      },
      "ports" : {
        "inputs" : [ {
          "id" : "EXP_CONV_2_in0",
          "slug" : "in0"
        } ],
        "outputs" : [ {
          "id" : "EXP_CONV_2_out0",
          "slug" : "out0"
        } ],
        "isCustomOutputSchema" : false,
        "autoUpdateOnRun" : false
      }
    },
    "MINERVA_EXCEPTION_NEW_RECORD_EXP" : {
      "id" : "MINERVA_EXCEPTION_NEW_RECORD_EXP",
      "component" : "Reformat",
      "metadata" : {
        "label" : "MINERVA_EXCEPTION_NEW_RECORD_EXP",
        "x" : 2520,
        "y" : 1020,
        "phase" : 1
      },
      "properties" : {
        "columnsSelector" : [ ],
        "expressions" : [ {
          "expression" : {
            "expression" : "CLASS",
            "_row_id" : null
          },
          "alias" : "CLASS",
          "description" : null,
          "_row_id" : "vyJ6_4bhXIjauD8p9GgE4"
        }, {
          "expression" : {
            "expression" : "BUSINESS_DATE",
            "_row_id" : null
          },
          "alias" : "BUSINESS_DATE",
          "description" : null,
          "_row_id" : "Yi50kb9FP0k7uEMvwRsjc"
        }, {
          "expression" : {
            "expression" : "CLID",
            "_row_id" : null
          },
          "alias" : "CLID",
          "description" : null,
          "_row_id" : "3dcVxQM3PiRzaZSst5rya"
        }, {
          "expression" : {
            "expression" : "CAST(NULL AS NUMERIC)",
            "_row_id" : null
          },
          "alias" : "ACCID",
          "description" : null,
          "_row_id" : "JMEtj2Si1p6ENX1zn1XdG"
        }, {
          "expression" : {
            "expression" : "CAST(NULL AS NUMERIC)",
            "_row_id" : null
          },
          "alias" : "ADID",
          "description" : null,
          "_row_id" : "e4_MQcteWlVnWlD78Y_Ws"
        }, {
          "expression" : {
            "expression" : "SOURCE_SYSTEM_CODE",
            "_row_id" : null
          },
          "alias" : "SOURCE_SYSTEM_CODE",
          "description" : null,
          "_row_id" : "94hgh4Z0Yh98gzMciiLqx"
        }, {
          "expression" : {
            "expression" : "SOURCE_CLIENT_REF",
            "_row_id" : null
          },
          "alias" : "SOURCE_CLIENT_REF",
          "description" : null,
          "_row_id" : "P4_lQ76RF0NxN7jAExzi_"
        }, {
          "expression" : {
            "expression" : "CAST(NULL AS STRING)",
            "_row_id" : null
          },
          "alias" : "ACCOUNT_ALIAS_ID",
          "description" : null,
          "_row_id" : "isK_1ScuNhsQUd5Cc5nv-"
        }, {
          "expression" : {
            "expression" : "ERROR_NUMBER",
            "_row_id" : null
          },
          "alias" : "ERROR_NUMBER",
          "description" : null,
          "_row_id" : "9eMBYHBVRcKFNJP_KwqOu"
        }, {
          "expression" : {
            "expression" : "PROCESS_NAME",
            "_row_id" : null
          },
          "alias" : "PROCESS_NAME",
          "description" : null,
          "_row_id" : "M6tEH2zpY3-PDlBkqVfe-"
        }, {
          "expression" : {
            "expression" : "FUNCTION_NAME",
            "_row_id" : null
          },
          "alias" : "FUNCTION_NAME",
          "description" : null,
          "_row_id" : "88uSgMLGj5sXnxge6uBF2"
        }, {
          "expression" : {
            "expression" : "CAST(NULL AS STRING)",
            "_row_id" : null
          },
          "alias" : "ADDITIONAL_IDENTIFIER",
          "description" : null,
          "_row_id" : "DRuFANVQBtBmQTXw-MqSL"
        }, {
          "expression" : {
            "expression" : "CAST(NULL AS NUMERIC)",
            "_row_id" : null
          },
          "alias" : "ADDITIONAL_IDENTIFIER_TYPE",
          "description" : null,
          "_row_id" : "bPPN9u3z1zdCnUBWl9Bzw"
        }, {
          "expression" : {
            "expression" : "LOAD_INDICATOR",
            "_row_id" : null
          },
          "alias" : "LOAD_INDICATOR",
          "description" : null,
          "_row_id" : "YdzN955u3CryCwOJbzF6_"
        }, {
          "expression" : {
            "expression" : "EXCEPTION_COMMENT",
            "_row_id" : null
          },
          "alias" : "EXCEPTION_COMMENT",
          "description" : null,
          "_row_id" : "d5iHgofvLca8rJWTWNVOz"
        } ]
      },
      "ports" : {
        "inputs" : [ {
          "id" : "MINERVA_EXCEPTION_NEW_RECORD_EXP_in0",
          "slug" : "in0"
        } ],
        "outputs" : [ {
          "id" : "MINERVA_EXCEPTION_NEW_RECORD_EXP_out0",
          "slug" : "out0"
        } ],
        "isCustomOutputSchema" : false,
        "autoUpdateOnRun" : false
      }
    },
    "FLT_FORENAMES_TEST1" : {
      "id" : "FLT_FORENAMES_TEST1",
      "component" : "Filter",
      "metadata" : {
        "label" : "FLT_FORENAMES_TEST1",
        "x" : 2120,
        "y" : 1020,
        "phase" : 1
      },
      "properties" : {
        "columnsSelector" : [ ],
        "condition" : {
          "expression" : "CAST((SURNAME = 'Customer') AS BOOL)",
          "_row_id" : null
        }
      },
      "ports" : {
        "inputs" : [ {
          "id" : "FLT_FORENAMES_TEST1_in0",
          "slug" : "in0"
        } ],
        "outputs" : [ {
          "id" : "FLT_FORENAMES_TEST1_out0",
          "slug" : "out0"
        } ],
        "isCustomOutputSchema" : false,
        "autoUpdateOnRun" : false
      }
    },
    "EXP_CARDSORIG_CLIENT_EXPR_14" : {
      "id" : "EXP_CARDSORIG_CLIENT_EXPR_14",
      "component" : "Reformat",
      "metadata" : {
        "label" : "EXP_CARDSORIG_CLIENT_EXPR_14",
        "x" : 1920,
        "y" : 1020,
        "phase" : 1
      },
      "properties" : {
        "columnsSelector" : [ ],
        "expressions" : [ {
          "expression" : {
            "expression" : "SURNAME",
            "_row_id" : null
          },
          "alias" : "SURNAME",
          "description" : null,
          "_row_id" : "KSteg0PREVpFuz68JD8LP"
        }, {
          "expression" : {
            "expression" : "CLID",
            "_row_id" : null
          },
          "alias" : "CLID",
          "description" : null,
          "_row_id" : "K9JTVO7H0H5rRfaZ_TYSF"
        }, {
          "expression" : {
            "expression" : "business_date",
            "_row_id" : null
          },
          "alias" : "business_date",
          "description" : null,
          "_row_id" : "j87_nvmKRSHd11O370Nwi"
        }, {
          "expression" : {
            "expression" : "CUSTOMER_NUMBER",
            "_row_id" : null
          },
          "alias" : "SOURCE_CUSTOMER_REF",
          "description" : null,
          "_row_id" : "JM1cRjzuoeXF2EoPcgKwX"
        }, {
          "expression" : {
            "expression" : "count1",
            "_row_id" : null
          },
          "alias" : "count1",
          "description" : null,
          "_row_id" : "tzDPOuR9uKmYfr0M6Q7ec"
        }, {
          "expression" : {
            "expression" : "lookup_string",
            "_row_id" : null
          },
          "alias" : "lookup_string",
          "description" : null,
          "_row_id" : "j1NVEJPloEfI6Ef3XUP2t"
        }, {
          "expression" : {
            "expression" : "businessdate",
            "_row_id" : null
          },
          "alias" : "businessdate",
          "description" : null,
          "_row_id" : "LYumnnYMJqlzcAO7LdKbT"
        }, {
          "expression" : {
            "expression" : "business_date_string",
            "_row_id" : null
          },
          "alias" : "business_date_string",
          "description" : null,
          "_row_id" : "OoVKkWs74Z09J0qP8muwj"
        }, {
          "expression" : {
            "expression" : "MERGE_CLID",
            "_row_id" : null
          },
          "alias" : "MERGE_CLID",
          "description" : null,
          "_row_id" : "U6ON_wTm-j0_tntwJ2KPw"
        }, {
          "expression" : {
            "expression" : "EFROM",
            "_row_id" : null
          },
          "alias" : "EFROM",
          "description" : null,
          "_row_id" : "CIgvhM99IxXCy0QBleKqy"
        }, {
          "expression" : {
            "expression" : "GENDER",
            "_row_id" : null
          },
          "alias" : "GENDER",
          "description" : null,
          "_row_id" : "mJJRw-yynyZ6c9Dc6aBmB"
        }, {
          "expression" : {
            "expression" : "CLID_LKP",
            "_row_id" : null
          },
          "alias" : "CLID_LKP",
          "description" : null,
          "_row_id" : "ntKimKGqijK9mkHg9bwE0"
        }, {
          "expression" : {
            "expression" : "TITLE_LKP",
            "_row_id" : null
          },
          "alias" : "TITLE_LKP",
          "description" : null,
          "_row_id" : "dzojdWT1Z-haE7H937UbB"
        }, {
          "expression" : {
            "expression" : "SURNAME_LKP",
            "_row_id" : null
          },
          "alias" : "SURNAME_LKP",
          "description" : null,
          "_row_id" : "Pa1RFlE_iH2BvJrGvtEc2"
        }, {
          "expression" : {
            "expression" : "TITLE",
            "_row_id" : null
          },
          "alias" : "TITLE",
          "description" : null,
          "_row_id" : "e4ITdJxqd039_rUcLOLSp"
        }, {
          "expression" : {
            "expression" : "INITIALS",
            "_row_id" : null
          },
          "alias" : "INITIALS",
          "description" : null,
          "_row_id" : "gAxADERyWJiJ8irp9D_cA"
        }, {
          "expression" : {
            "expression" : "FORENAMES",
            "_row_id" : null
          },
          "alias" : "FORENAMES",
          "description" : null,
          "_row_id" : "LmUWyBtIsaZ7Vo-QlNqYj"
        }, {
          "expression" : {
            "expression" : "DOB",
            "_row_id" : null
          },
          "alias" : "DOB",
          "description" : null,
          "_row_id" : "oEKzXm8eO32M7zBah6ATz"
        }, {
          "expression" : {
            "expression" : "CLIENT_CLASS",
            "_row_id" : null
          },
          "alias" : "CLIENT_CLASS",
          "description" : null,
          "_row_id" : "WhKkQxaaA-U4IbN_L8uO_"
        }, {
          "expression" : {
            "expression" : "SOURCE_TYPE",
            "_row_id" : null
          },
          "alias" : "SOURCE_TYPE",
          "description" : null,
          "_row_id" : "N3uvXJ0SFIRfW3RxryzS3"
        }, {
          "expression" : {
            "expression" : "SOURCE_SYSTEM_CODE",
            "_row_id" : null
          },
          "alias" : "SOURCE_SYSTEM_CODE",
          "description" : null,
          "_row_id" : "ZqyHt6S_kSd_o3n5sMS-g"
        }, {
          "expression" : {
            "expression" : "SOURCE_RECORD_TYPE",
            "_row_id" : null
          },
          "alias" : "SOURCE_RECORD_TYPE",
          "description" : null,
          "_row_id" : "SGRWf7z4rbkHn5-pY4nLI"
        }, {
          "expression" : {
            "expression" : "CLIENT_STATUS",
            "_row_id" : null
          },
          "alias" : "CLIENT_STATUS",
          "description" : null,
          "_row_id" : "3QVIXb_OMMfSA-yYmJcx4"
        }, {
          "expression" : {
            "expression" : "feed_update_id",
            "_row_id" : null
          },
          "alias" : "feed_update_id",
          "description" : null,
          "_row_id" : "6hNe8MCFQzUUPsl0YK17e"
        }, {
          "expression" : {
            "expression" : "business_date_minus_1",
            "_row_id" : null
          },
          "alias" : "business_date_minus_1",
          "description" : null,
          "_row_id" : "yttKLxRIQl3zzdcV6KcME"
        }, {
          "expression" : {
            "expression" : "TOTAL_COMPARE",
            "_row_id" : null
          },
          "alias" : "TOTAL_COMPARE",
          "description" : null,
          "_row_id" : "GnK5es50oxzU9RPe01_sE"
        }, {
          "expression" : {
            "expression" : "BUSINESS_DATE_CHK",
            "_row_id" : null
          },
          "alias" : "BUSINESS_DATE_CHK",
          "description" : null,
          "_row_id" : "Xho5IZDv7yPLCXTrvYSPO"
        }, {
          "expression" : {
            "expression" : "prophecy_sk",
            "_row_id" : null
          },
          "alias" : "prophecy_sk",
          "description" : null,
          "_row_id" : "Dhc4hM3ehhNbLFskGZ8Pz"
        } ]
      },
      "ports" : {
        "inputs" : [ {
          "id" : "EXP_CARDSORIG_CLIENT_EXPR_14_in0",
          "slug" : "in0"
        } ],
        "outputs" : [ {
          "id" : "EXP_CARDSORIG_CLIENT_EXPR_14_out0",
          "slug" : "out0"
        } ],
        "isCustomOutputSchema" : false,
        "autoUpdateOnRun" : false
      }
    },
    "EXP_CARDSORIG_CLIENT_EXP_CARDSORIG_CLIENT_out0" : {
      "id" : "EXP_CARDSORIG_CLIENT_EXP_CARDSORIG_CLIENT_out0",
      "component" : "SQLStatement",
      "metadata" : {
        "label" : "EXP_CARDSORIG_CLIENT"
      },
      "properties" : {
        "fileTabs" : [ {
          "path" : "output_port_3",
          "id" : "output_port_3",
          "language" : "sql",
          "content" : "\nSELECT *\n\nFROM {{ ref('m_rep_cards_orig_client_staging_update__EXP_CARDSORIG_CLIENT') }}\n\n"
        } ]
      },
      "ports" : {
        "inputs" : [ {
          "id" : "input_port_3",
          "slug" : "input_port_3"
        } ],
        "outputs" : [ {
          "id" : "output_port_3",
          "slug" : "output_port_3"
        } ],
        "isCustomOutputSchema" : false,
        "autoUpdateOnRun" : false
      }
    }
  },
  "connections" : [ {
    "id" : "edge_54",
    "source" : "MINERVA_EXCEPTION_NEW_RECORD_EXP",
    "sourcePort" : "MINERVA_EXCEPTION_NEW_RECORD_EXP_out0",
    "target" : "MINERVA_EXCEPTION_NEW_RECORD",
    "targetPort" : "MINERVA_EXCEPTION_NEW_RECORD_in0",
    "isWireless" : false
  }, {
    "id" : "edge_48",
    "source" : "EXP_CONV_2",
    "sourcePort" : "EXP_CONV_2_out0",
    "target" : "MINERVA_EXCEPTION_NEW_RECORD_EXP",
    "targetPort" : "MINERVA_EXCEPTION_NEW_RECORD_EXP_in0",
    "isWireless" : false
  }, {
    "id" : "edge_59",
    "source" : "FLT_FORENAMES_TEST1",
    "sourcePort" : "FLT_FORENAMES_TEST1_out0",
    "target" : "EXP_CONV_2",
    "targetPort" : "EXP_CONV_2_in0",
    "isWireless" : false
  }, {
    "id" : "edge_61",
    "source" : "EXP_CARDSORIG_CLIENT_EXPR_14",
    "sourcePort" : "EXP_CARDSORIG_CLIENT_EXPR_14_out0",
    "target" : "FLT_FORENAMES_TEST1",
    "targetPort" : "FLT_FORENAMES_TEST1_in0",
    "isWireless" : false
  }, {
    "id" : "edge_60",
    "source" : "EXP_CARDSORIG_CLIENT_EXP_CARDSORIG_CLIENT_out0",
    "sourcePort" : "output_port_3",
    "target" : "EXP_CARDSORIG_CLIENT_EXPR_14",
    "targetPort" : "EXP_CARDSORIG_CLIENT_EXPR_14_in0",
    "isWireless" : false
  } ],
  "component" : "Model"
}