{
  "id" : "challenge_154_solution_DL__AlteryxSelect_57",
  "metainfo" : {
    "label" : "challenge_154_solution_DL__AlteryxSelect_57",
    "autoLayout" : true,
    "staleState" : "none",
    "sourceSuggestions" : {
      "sources" : [ ]
    },
    "graphConfig" : {
      "entityConfig" : {
        "materialized" : "ephemeral",
        "database" : "\"prophecy-databricks-qa\"",
        "schema" : "\"anurag_test\"",
        "type" : "ModelConfig"
      }
    },
    "version" : 3
  },
  "processes" : {
    "51" : {
      "id" : "51",
      "component" : "Regex",
      "metadata" : {
        "label" : "RegEx_51",
        "x" : 1860,
        "y" : 288,
        "phase" : 0
      },
      "properties" : {
        "outputMethod" : "tokenize",
        "tokenizeOutputMethod" : "splitRows",
        "copyUnmatchedText" : false,
        "caseInsensitive" : true,
        "matchColumnName" : "",
        "parseColumns" : [ {
          "columnName" : "regex_col1",
          "dataType" : "string",
          "rgxExpression" : "(.)"
        } ],
        "relation_name" : [ "Formula_50_0" ],
        "errorIfNotMatched" : false,
        "noOfColumns" : 1,
        "_oldMacroProperties" : {
          "macroName" : "Regex",
          "projectName" : "prophecy_basics",
          "parameters" : [ {
            "name" : "relation_name",
            "value" : "[\"Formula_50_0\"]"
          }, {
            "name" : "parseColumns",
            "value" : "[{\"columnName\": \"regex_col1\", \"dataType\": \"string\", \"rgxExpression\": \"(.)\"}]"
          }, {
            "name" : "schema",
            "value" : "[{\"name\": \"Bin\", \"dataType\": \"String\"}, {\"name\": \"Scenario\", \"dataType\": \"Numeric\"}, {\"name\": \"Count\", \"dataType\": \"Numeric\"}]"
          }, {
            "name" : "selectedColumnName",
            "value" : "Bin"
          }, {
            "name" : "outputMethod",
            "value" : "tokenize"
          }, {
            "name" : "regexExpression",
            "value" : "(.)"
          }, {
            "name" : "caseInsensitive",
            "value" : "true"
          }, {
            "name" : "replacementText",
            "value" : ""
          }, {
            "name" : "copyUnmatchedText",
            "value" : "false"
          }, {
            "name" : "tokenizeOutputMethod",
            "value" : "splitRows"
          }, {
            "name" : "allowBlankTokens",
            "value" : "false"
          }, {
            "name" : "noOfColumns",
            "value" : "1"
          }, {
            "name" : "extraColumnsHandling",
            "value" : "dropExtraWithoutWarning"
          }, {
            "name" : "outputRootName",
            "value" : "generated"
          }, {
            "name" : "matchColumnName",
            "value" : ""
          }, {
            "name" : "errorIfNotMatched",
            "value" : "false"
          } ]
        },
        "splitRowsColumnName" : "generated_column",
        "schema" : "[{\"name\": \"Bin\", \"dataType\": \"String\"}, {\"name\": \"Scenario\", \"dataType\": \"Numeric\"}, {\"name\": \"Count\", \"dataType\": \"Numeric\"}]",
        "allowBlankTokens" : false,
        "outputRootName" : "generated",
        "extraColumnsHandling" : "dropExtraWithoutWarning",
        "replacementText" : "",
        "selectedColumnName" : "Bin",
        "regexExpression" : "(.)"
      },
      "ports" : {
        "inputs" : [ {
          "id" : "51_Input",
          "slug" : "in0"
        } ],
        "outputs" : [ {
          "id" : "51_Output",
          "slug" : "out0"
        } ],
        "isCustomOutputSchema" : false,
        "autoUpdateOnRun" : false
      }
    },
    "RecordID_52_52_Output" : {
      "id" : "RecordID_52_52_Output",
      "component" : "SQLStatement",
      "metadata" : {
        "label" : "RecordID_52"
      },
      "properties" : {
        "fileTabs" : [ {
          "path" : "output_port_1",
          "id" : "output_port_1",
          "language" : "sql",
          "content" : "\nSELECT *\n\nFROM {{ ref('challenge_154_solution_DL__RecordID_52') }}\n\n"
        } ]
      },
      "ports" : {
        "inputs" : [ {
          "id" : "input_port_1",
          "slug" : "input_port_1"
        } ],
        "outputs" : [ {
          "id" : "output_port_1",
          "slug" : "output_port_1"
        } ],
        "isCustomOutputSchema" : false,
        "autoUpdateOnRun" : false
      }
    },
    "56" : {
      "id" : "56",
      "component" : "OrderBy",
      "metadata" : {
        "label" : "Sort_56",
        "x" : 1620,
        "y" : 792,
        "phase" : 0
      },
      "properties" : {
        "columnsSelector" : [ ],
        "orders" : [ {
          "expression" : {
            "expression" : "CAST(Scenario AS STRING)",
            "_row_id" : null
          },
          "sortType" : "asc",
          "nullsType" : ""
        }, {
          "expression" : {
            "expression" : "CAST(RecordID AS STRING)",
            "_row_id" : null
          },
          "sortType" : "asc",
          "nullsType" : ""
        } ]
      },
      "ports" : {
        "inputs" : [ {
          "id" : "56_Input",
          "slug" : "in0"
        } ],
        "outputs" : [ {
          "id" : "56_Output",
          "slug" : "out0"
        } ],
        "isCustomOutputSchema" : false,
        "autoUpdateOnRun" : false
      }
    },
    "54" : {
      "id" : "54",
      "component" : "ToDo",
      "metadata" : {
        "label" : "MultiRowFormula_54",
        "x" : 2460,
        "y" : 288,
        "phase" : 0
      },
      "properties" : {
        "relation_name" : [ "MultiRowFormula_54_row_id_0" ],
        "code_string" : "<Node ToolID=\"54\">\n      <GuiSettings Plugin=\"AlteryxBasePluginsGui.MultiRowFormula.MultiRowFormula\">\n        <Position y=\"462\" x=\"594\"/>\n      </GuiSettings>\n      <Properties>\n        <Configuration>\n          <UpdateField value=\"False\"/>\n          <UpdateField_Name>Count</UpdateField_Name>\n          <CreateField_Name>RecordID</CreateField_Name>\n          <CreateField_Type>Int32</CreateField_Type>\n          <CreateField_Size>4</CreateField_Size>\n          <OtherRows>Empty</OtherRows>\n          <NumRows value=\"1\"/>\n          <Expression>[Row-1:RecordID]+1</Expression>\n          <GroupByFields>\n            <Field field=\"Scenario\"/>\n          </GroupByFields>\n        </Configuration>\n        <Annotation DisplayMode=\"0\">\n          <Name/>\n          <AnnotationText>RecordId to match to input</AnnotationText>\n          <DefaultAnnotationText>[Row-1:RecordID]+1</DefaultAnnotationText>\n          <Left value=\"False\"/>\n        </Annotation>\n      </Properties>\n      <EngineSettings EngineDllEntryPoint=\"AlteryxMultiRowFormula\" EngineDll=\"AlteryxBasePluginsEngine.dll\"/>\n    </Node>",
        "diag_message" : "Multi Row Formula tool for this case is not supported by transpiler in SQL",
        "error_string" : "Multi Row Formula tool for this case is not supported by transpiler in SQL"
      },
      "ports" : {
        "inputs" : [ {
          "id" : "54_Input",
          "slug" : "in0"
        } ],
        "outputs" : [ {
          "id" : "54_Output",
          "slug" : "out0"
        } ],
        "isCustomOutputSchema" : false,
        "autoUpdateOnRun" : false
      }
    },
    "57" : {
      "id" : "57",
      "component" : "Reformat",
      "metadata" : {
        "label" : "AlteryxSelect_57",
        "x" : 1860,
        "y" : 792,
        "phase" : 0
      },
      "properties" : {
        "columnsSelector" : [ ],
        "expressions" : [ {
          "expression" : {
            "expression" : "* EXCEPT(`Count`, `RecordID`)",
            "_row_id" : null
          },
          "alias" : null,
          "description" : null,
          "_row_id" : null
        } ]
      },
      "ports" : {
        "inputs" : [ {
          "id" : "57_Input",
          "slug" : "in0"
        } ],
        "outputs" : [ {
          "id" : "3AUHne_3SJ3b-eS1hGAei",
          "slug" : "out0"
        } ],
        "isCustomOutputSchema" : false,
        "autoUpdateOnRun" : false
      }
    },
    "oAAHYHCq9RtER7eDDjs9u" : {
      "id" : "oAAHYHCq9RtER7eDDjs9u",
      "component" : "Reformat",
      "metadata" : {
        "label" : "Formula_53_0",
        "x" : 3300,
        "y" : 288,
        "phase" : 0
      },
      "properties" : {
        "columnsSelector" : [ ],
        "expressions" : [ {
          "expression" : {
            "expression" : "CAST((CASE WHEN (Bin = '0') THEN 'Off' ELSE 'On ' END) AS STRING)",
            "_row_id" : null
          },
          "alias" : "Bin",
          "description" : null,
          "_row_id" : "adIuMP5UdRUEMhM0Dnqct"
        }, {
          "expression" : {
            "expression" : "* EXCEPT(`bin`)",
            "_row_id" : null
          },
          "alias" : null,
          "description" : null,
          "_row_id" : null
        } ]
      },
      "ports" : {
        "inputs" : [ {
          "id" : "CMoi1W2HUtzsX3yb7DBkO",
          "slug" : "in0"
        } ],
        "outputs" : [ {
          "id" : "EhRwk3uc3DAk3BsIv0i3N",
          "slug" : "out"
        } ],
        "isCustomOutputSchema" : false,
        "autoUpdateOnRun" : false
      }
    },
    "AlteryxSelect_57_3AUHne_3SJ3b-eS1hGAei" : {
      "id" : "AlteryxSelect_57_3AUHne_3SJ3b-eS1hGAei",
      "component" : "TargetModel",
      "metadata" : {
        "label" : "AlteryxSelect_57"
      },
      "properties" : {
        "customQueryDisabled" : true,
        "customQuery" : false,
        "incrementalEditorDisabled" : true,
        "query" : "\nSELECT *\n\nFROM AlteryxSelect_57\n\n",
        "isModel" : true,
        "incrementalKey" : false,
        "incremental" : {
          "expression" : "true"
        }
      },
      "ports" : {
        "inputs" : [ {
          "id" : "input_port_4",
          "slug" : "input_port_4"
        } ],
        "outputs" : [ {
          "id" : "output_port_4",
          "slug" : "output_port_4"
        } ],
        "isCustomOutputSchema" : false,
        "autoUpdateOnRun" : false
      }
    },
    "GenerateRows_49_49_Output" : {
      "id" : "GenerateRows_49_49_Output",
      "component" : "SQLStatement",
      "metadata" : {
        "label" : "GenerateRows_49"
      },
      "properties" : {
        "fileTabs" : [ {
          "path" : "output_port_3",
          "id" : "output_port_3",
          "language" : "sql",
          "content" : "\nSELECT *\n\nFROM {{ prophecy_tmp_source('challenge_154_solution_DL', 'GenerateRows_49') }}\n\n"
        } ]
      },
      "ports" : {
        "inputs" : [ {
          "id" : "input_port_3",
          "slug" : "input_port_3"
        } ],
        "outputs" : [ {
          "id" : "output_port_3",
          "slug" : "output_port_3"
        } ],
        "isCustomOutputSchema" : false,
        "autoUpdateOnRun" : false
      }
    },
    "MyYHkGZfInH1gXPCHcc0v" : {
      "id" : "MyYHkGZfInH1gXPCHcc0v",
      "component" : "Reformat",
      "metadata" : {
        "label" : "RegEx_51_dropGem_0",
        "x" : 2040,
        "y" : 288,
        "phase" : 0
      },
      "properties" : {
        "columnsSelector" : [ ],
        "expressions" : [ {
          "expression" : {
            "expression" : "generated",
            "_row_id" : null
          },
          "alias" : "Bin",
          "description" : null,
          "_row_id" : "4mcRL3-dj-_ruwwY2l9cd"
        }, {
          "expression" : {
            "expression" : "* EXCEPT(`generated`, `token_position`, `token_sequence`, `bin`)",
            "_row_id" : null
          },
          "alias" : null,
          "description" : null,
          "_row_id" : null
        } ]
      },
      "ports" : {
        "inputs" : [ {
          "id" : "4HWPtb1JDWDnblGcaPs_P",
          "slug" : "in0"
        } ],
        "outputs" : [ {
          "id" : "drzxvlF0PaiRgwtFoDrYh",
          "slug" : "out"
        } ],
        "isCustomOutputSchema" : false,
        "autoUpdateOnRun" : false
      }
    },
    "tli3eGwsXLw9viRIPkEea" : {
      "id" : "tli3eGwsXLw9viRIPkEea",
      "component" : "Reformat",
      "metadata" : {
        "label" : "MultiRowFormula_54_row_id_drop_0",
        "x" : 2820,
        "y" : 288,
        "phase" : 0
      },
      "properties" : {
        "columnsSelector" : [ ],
        "expressions" : [ {
          "expression" : {
            "expression" : "* EXCEPT(`prophecy_row_id`)",
            "_row_id" : null
          },
          "alias" : null,
          "description" : null,
          "_row_id" : null
        } ]
      },
      "ports" : {
        "inputs" : [ {
          "id" : "H7dPwuKuLe5zN7dluGfnS",
          "slug" : "in0"
        } ],
        "outputs" : [ {
          "id" : "0JUwi0B6qdsH1ydxxl5yn",
          "slug" : "out"
        } ],
        "isCustomOutputSchema" : false,
        "autoUpdateOnRun" : false
      }
    },
    "55_inner" : {
      "id" : "55_inner",
      "component" : "Join",
      "metadata" : {
        "label" : "Join_55_inner",
        "x" : 1140,
        "y" : 792,
        "phase" : 0
      },
      "properties" : {
        "conditions" : [ {
          "alias" : "in1",
          "expression" : {
            "expression" : "(in0.RecordID = in1.RecordID)",
            "_row_id" : null
          },
          "joinType" : "inner",
          "rightAlias" : null
        } ],
        "allowSelection" : false,
        "expressions" : [ {
          "expression" : {
            "expression" : "in0.COUNT",
            "_row_id" : null
          },
          "alias" : "`Count`",
          "description" : null,
          "_row_id" : "FNDouAN3yrrifW24P8Rgj"
        }, {
          "expression" : {
            "expression" : "in0.Scenario",
            "_row_id" : null
          },
          "alias" : "Scenario",
          "description" : null,
          "_row_id" : "mmNsNZp3e7ctsbH9GnKVS"
        }, {
          "expression" : {
            "expression" : "in1.Options",
            "_row_id" : null
          },
          "alias" : "`Option 1`",
          "description" : null,
          "_row_id" : "dkHWHNOiS4L0GdZr_nGcE"
        }, {
          "expression" : {
            "expression" : "in0.Bin",
            "_row_id" : null
          },
          "alias" : "`Option 2`",
          "description" : null,
          "_row_id" : "FBXdO6nl0sK4SyvIskJo8"
        }, {
          "expression" : {
            "expression" : "in0.RecordID",
            "_row_id" : null
          },
          "alias" : "RecordID",
          "description" : null,
          "_row_id" : "6wvn9mKCFAhrgsFiUBezB"
        } ],
        "activeTab" : "conditions",
        "columnsSelector" : [ ],
        "headAlias" : "in0"
      },
      "ports" : {
        "inputs" : [ {
          "id" : "neB3F8LeUoeDdtxxmlhPU",
          "slug" : "in0"
        }, {
          "id" : "yemcpw3hRYTJP_358XDho",
          "slug" : "in1"
        } ],
        "outputs" : [ {
          "id" : "099ztMiHZE-XSydHN3SrS",
          "slug" : "out0"
        } ],
        "isCustomOutputSchema" : false,
        "autoUpdateOnRun" : false
      }
    },
    "yDUj8KUNJICevXgIwQGRa" : {
      "id" : "yDUj8KUNJICevXgIwQGRa",
      "component" : "Reformat",
      "metadata" : {
        "label" : "MultiRowFormula_54_row_id_0",
        "x" : 2280,
        "y" : 288,
        "phase" : 0
      },
      "properties" : {
        "columnsSelector" : [ ],
        "expressions" : [ {
          "expression" : {
            "expression" : "(ROW_NUMBER() OVER ())",
            "_row_id" : null
          },
          "alias" : "prophecy_row_id",
          "description" : null,
          "_row_id" : "ZGtxWqLXN78Zj6q8mwNzc"
        }, {
          "expression" : {
            "expression" : "*",
            "_row_id" : null
          },
          "alias" : null,
          "description" : null,
          "_row_id" : null
        } ]
      },
      "ports" : {
        "inputs" : [ {
          "id" : "m4W_L635LlSQkQVomQ10G",
          "slug" : "in0"
        } ],
        "outputs" : [ {
          "id" : "YS4cQZ6_8GsvRvRgGp0Un",
          "slug" : "out"
        } ],
        "isCustomOutputSchema" : false,
        "autoUpdateOnRun" : false
      }
    },
    "lZRmXXKx48B0QBFnWu-WA" : {
      "id" : "lZRmXXKx48B0QBFnWu-WA",
      "component" : "Reformat",
      "metadata" : {
        "label" : "Formula_50_0",
        "x" : 1380,
        "y" : 288,
        "phase" : 0
      },
      "properties" : {
        "columnsSelector" : [ "QcREPWUivgjL_gaVntqXr##Scenario" ],
        "expressions" : [ {
          "expression" : {
            "expression" : "CAST(REVERSE((bqutil.fn.to_binary(CAST(Scenario AS INT64)))) AS STRING)"
          },
          "alias" : "Bin",
          "_row_id" : "yT00Og-NYIqXShZLx2kay"
        }, {
          "expression" : {
            "expression" : "(Scenario + 1)"
          },
          "alias" : "Scenario",
          "_row_id" : "5EyYvWhMko-oZGwW37aVd"
        }, {
          "expression" : {
            "expression" : "* EXCEPT(`scenario`)"
          },
          "_row_id" : "1564956224"
        } ]
      },
      "ports" : {
        "inputs" : [ {
          "id" : "QcREPWUivgjL_gaVntqXr",
          "slug" : "in0"
        } ],
        "outputs" : [ {
          "id" : "uWi419gUqNoLdYDvyye7i",
          "slug" : "out"
        } ],
        "isCustomOutputSchema" : false,
        "autoUpdateOnRun" : false
      }
    }
  },
  "connections" : [ {
    "id" : "conn_57_3AUHne_3SJ3b-eS1hGAei_AlteryxSelect_57_3AUHne_3SJ3b-eS1hGAei",
    "source" : "57",
    "sourcePort" : "3AUHne_3SJ3b-eS1hGAei",
    "target" : "AlteryxSelect_57_3AUHne_3SJ3b-eS1hGAei",
    "targetPort" : "input_port_4",
    "isWireless" : false
  }, {
    "id" : "edge_56",
    "source" : "56",
    "sourcePort" : "56_Output",
    "target" : "57",
    "targetPort" : "57_Input",
    "isWireless" : false
  }, {
    "id" : "edge_58",
    "source" : "55_inner",
    "sourcePort" : "099ztMiHZE-XSydHN3SrS",
    "target" : "56",
    "targetPort" : "56_Input",
    "isWireless" : false
  }, {
    "id" : "edge_68",
    "source" : "oAAHYHCq9RtER7eDDjs9u",
    "sourcePort" : "EhRwk3uc3DAk3BsIv0i3N",
    "target" : "55_inner",
    "targetPort" : "neB3F8LeUoeDdtxxmlhPU",
    "isWireless" : false
  }, {
    "id" : "edge_57",
    "source" : "RecordID_52_52_Output",
    "sourcePort" : "output_port_1",
    "target" : "55_inner",
    "targetPort" : "yemcpw3hRYTJP_358XDho",
    "isWireless" : false
  }, {
    "id" : "edge_69",
    "source" : "tli3eGwsXLw9viRIPkEea",
    "sourcePort" : "0JUwi0B6qdsH1ydxxl5yn",
    "target" : "oAAHYHCq9RtER7eDDjs9u",
    "targetPort" : "CMoi1W2HUtzsX3yb7DBkO",
    "isWireless" : false
  }, {
    "id" : "edge_67",
    "source" : "54",
    "sourcePort" : "54_Output",
    "target" : "tli3eGwsXLw9viRIPkEea",
    "targetPort" : "H7dPwuKuLe5zN7dluGfnS",
    "isWireless" : false
  }, {
    "id" : "edge_65",
    "source" : "yDUj8KUNJICevXgIwQGRa",
    "sourcePort" : "YS4cQZ6_8GsvRvRgGp0Un",
    "target" : "54",
    "targetPort" : "54_Input",
    "isWireless" : false
  }, {
    "id" : "edge_66",
    "source" : "MyYHkGZfInH1gXPCHcc0v",
    "sourcePort" : "drzxvlF0PaiRgwtFoDrYh",
    "target" : "yDUj8KUNJICevXgIwQGRa",
    "targetPort" : "m4W_L635LlSQkQVomQ10G",
    "isWireless" : false
  }, {
    "id" : "edge_64",
    "source" : "51",
    "sourcePort" : "51_Output",
    "target" : "MyYHkGZfInH1gXPCHcc0v",
    "targetPort" : "4HWPtb1JDWDnblGcaPs_P",
    "isWireless" : false
  }, {
    "id" : "edge_62",
    "source" : "lZRmXXKx48B0QBFnWu-WA",
    "sourcePort" : "uWi419gUqNoLdYDvyye7i",
    "target" : "51",
    "targetPort" : "51_Input",
    "isWireless" : false
  }, {
    "id" : "edge_63",
    "source" : "GenerateRows_49_49_Output",
    "sourcePort" : "output_port_3",
    "target" : "lZRmXXKx48B0QBFnWu-WA",
    "targetPort" : "QcREPWUivgjL_gaVntqXr",
    "isWireless" : false
  } ],
  "component" : "Model"
}